{"nodes": [{"group": 10000, "name": 10000}, {"group": 8, "name": 8}, {"group": 8, "name": 3}, {"group": 8, "name": 4}, {"group": 8, "name": 9}, {"group": 8, "name": 10}, {"group": 1, "name": 1}, {"group": 1, "name": 2}, {"group": 7, "name": 7}, {"group": 7, "name": 0}, {"group": 7, "name": 5}, {"group": 15, "name": 15}, {"group": 15, "name": 6}, {"group": 15, "name": 11}, {"group": 15, "name": 12}, {"group": 15, "name": 13}, {"group": 15, "name": 14}], "links": [{"source": 0, "target": 1, "value": 8}, {"source": 1, "target": 2, "value": 6}, {"source": 1, "target": 3, "value": 6}, {"source": 1, "target": 4, "value": 6}, {"source": 1, "target": 5, "value": 6}, {"source": 0, "target": 6, "value": 8}, {"source": 6, "target": 7, "value": 6}, {"source": 0, "target": 8, "value": 8}, {"source": 8, "target": 9, "value": 6}, {"source": 8, "target": 10, "value": 6}, {"source": 0, "target": 11, "value": 8}, {"source": 11, "target": 12, "value": 6}, {"source": 11, "target": 13, "value": 6}, {"source": 11, "target": 14, "value": 6}, {"source": 11, "target": 15, "value": 6}, {"source": 11, "target": 16, "value": 6}]}